{
  "words": {
    "symptom": {
      "word": "symptom",
      "meaning": "症状",
      "ipa": "/ˈsɪmptəm/",
      "example": "What are your symptoms?",
      "ease_factor": 2.5,
      "repetitions": 0,
      "interval": 1,
      "next_review": "2026-05-17",
      "last_quality": 0,
      "review_count": 0,
      "added": "2026-05-17"
    },
    "basically": {
      "word": "basically",
      "meaning": "基本上",
      "ipa": "/ˈbeɪsɪkli/",
      "example": "Basically, yes.",
      "ease_factor": 2.5,
      "repetitions": 0,
      "interval": 1,
      "next_review": "2026-05-17",
      "last_quality": 0,
      "review_count": 0,
      "added": "2026-05-17"
    },
    "sunset": {
      "word": "sunset",
      "meaning": "来自TED深度课",
      "ipa": "",
      "example": "",
      "ease_factor": 2.5,
      "repetitions": 0,
      "interval": 1,
      "next_review": "2026-05-17",
      "last_quality": 0,
      "review_count": 0,
      "added": "2026-05-17"
    },
    "american": {
      "word": "american",
      "meaning": "来自TED深度课",
      "ipa": "",
      "example": "",
      "ease_factor": 2.5,
      "repetitions": 0,
      "interval": 1,
      "next_review": "2026-05-17",
      "last_quality": 0,
      "review_count": 0,
      "added": "2026-05-17"
    },
    "october": {
      "word": "october",
      "meaning": "来自TED深度课",
      "ipa": "",
      "example": "",
      "ease_factor": 2.5,
      "repetitions": 0,
      "interval": 1,
      "next_review": "2026-05-17",
      "last_quality": 0,
      "review_count": 0,
      "added": "2026-05-17"
    },
    "national": {
      "word": "national",
      "meaning": "来自TED深度课",
      "ipa": "",
      "example": "",
      "ease_factor": 2.5,
      "repetitions": 0,
      "interval": 1,
      "next_review": "2026-05-17",
      "last_quality": 0,
      "review_count": 0,
      "added": "2026-05-17"
    },
    "yulieski": {
      "word": "yulieski",
      "meaning": "来自TED深度课",
      "ipa": "",
      "example": "",
      "ease_factor": 2.5,
      "repetitions": 0,
      "interval": 1,
      "next_review": "2026-05-17",
      "last_quality": 0,
      "review_count": 0,
      "added": "2026-05-17"
    },
    "habana": {
      "word": "habana",
      "meaning": "来自TED深度课",
      "ipa": "",
      "example": "",
      "ease_factor": 2.5,
      "repetitions": 0,
      "interval": 1,
      "next_review": "2026-05-17",
      "last_quality": 0,
      "review_count": 0,
      "added": "2026-05-17"
    },
    "series": {
      "word": "series",
      "meaning": "来自TED深度课",
      "ipa": "",
      "example": "",
      "ease_factor": 2.5,
      "repetitions": 0,
      "interval": 1,
      "next_review": "2026-05-17",
      "last_quality": 0,
      "review_count": 0,
      "added": "2026-05-17"
    },
    "ledesma": {
      "word": "ledesma",
      "meaning": "来自TED深度课",
      "ipa": "",
      "example": "",
      "ease_factor": 2.5,
      "repetitions": 0,
      "interval": 1,
      "next_review": "2026-05-17",
      "last_quality": 0,
      "review_count": 0,
      "added": "2026-05-17"
    },
    "unlike": {
      "word": "unlike",
      "meaning": "来自TED深度课",
      "ipa": "",
      "example": "",
      "ease_factor": 2.5,
      "repetitions": 0,
      "interval": 1,
      "next_review": "2026-05-17",
      "last_quality": 0,
      "review_count": 0,
      "added": "2026-05-17"
    },
    "alternative": {
      "word": "alternative",
      "meaning": "来自TED深度课",
      "ipa": "",
      "example": "",
      "ease_factor": 2.5,
      "repetitions": 0,
      "interval": 1,
      "next_review": "2026-05-17",
      "last_quality": 0,
      "review_count": 0,
      "added": "2026-05-17"
    },
    "Medical": {
      "word": "Medical",
      "meaning": "请查阅词典",
      "ipa": "",
      "example": "",
      "ease_factor": 2.5,
      "repetitions": 0,
      "interval": 1,
      "next_review": "2026-05-17",
      "last_quality": 0,
      "review_count": 0,
      "added": "2026-05-17"
    },
    "artificial": {
      "word": "artificial",
      "meaning": "来自TED深度课",
      "ipa": "",
      "example": "",
      "ease_factor": 2.5,
      "repetitions": 0,
      "interval": 1,
      "next_review": "2026-05-17",
      "last_quality": 0,
      "review_count": 0,
      "added": "2026-05-17"
    },
    "Cabinet": {
      "word": "Cabinet",
      "meaning": "内阁",
      "ipa": "/ˈkæbɪnət/",
      "example": "",
      "ease_factor": 2.5,
      "repetitions": 0,
      "interval": 1,
      "next_review": "2026-05-17",
      "last_quality": 0,
      "review_count": 0,
      "added": "2026-05-17"
    },
    "Secretary": {
      "word": "Secretary",
      "meaning": "秘书；大臣",
      "ipa": "/ˈsekrəteri/",
      "example": "",
      "ease_factor": 2.5,
      "repetitions": 0,
      "interval": 1,
      "next_review": "2026-05-17",
      "last_quality": 0,
      "review_count": 0,
      "added": "2026-05-17"
    },
    "Finance": {
      "word": "Finance",
      "meaning": "财政；金融",
      "ipa": "/ˈfaɪnæns/",
      "example": "",
      "ease_factor": 2.5,
      "repetitions": 0,
      "interval": 1,
      "next_review": "2026-05-17",
      "last_quality": 0,
      "review_count": 0,
      "added": "2026-05-17"
    },
    "Ministerial": {
      "word": "Ministerial",
      "meaning": "部长的；内阁的",
      "ipa": "/ˌmɪnɪˈstɪəriəl/",
      "example": "",
      "ease_factor": 2.5,
      "repetitions": 0,
      "interval": 1,
      "next_review": "2026-05-17",
      "last_quality": 0,
      "review_count": 0,
      "added": "2026-05-17"
    },
    "Directorate": {
      "word": "Directorate",
      "meaning": "部门；理事会",
      "ipa": "/daɪˈrektərət/",
      "example": "",
      "ease_factor": 2.5,
      "repetitions": 0,
      "interval": 1,
      "next_review": "2026-05-17",
      "last_quality": 0,
      "review_count": 0,
      "added": "2026-05-17"
    },
    "high-profile": {
      "word": "high-profile",
      "meaning": "知名的，高调的",
      "ipa": "/haɪˈproʊfaɪl/",
      "example": "",
      "ease_factor": 2.5,
      "repetitions": 0,
      "interval": 1,
      "next_review": "2026-05-17",
      "last_quality": 0,
      "review_count": 0,
      "added": "2026-05-17"
    },
    "forthcoming": {
      "word": "forthcoming",
      "meaning": "即将出版的",
      "ipa": "/fɔːrθˈkʌmɪŋ/",
      "example": "",
      "ease_factor": 2.5,
      "repetitions": 0,
      "interval": 1,
      "next_review": "2026-05-17",
      "last_quality": 0,
      "review_count": 0,
      "added": "2026-05-17"
    },
    "investigate": {
      "word": "investigate",
      "meaning": "调查",
      "ipa": "/ɪnˈvestɪɡeɪt/",
      "example": "",
      "ease_factor": 2.5,
      "repetitions": 0,
      "interval": 1,
      "next_review": "2026-05-17",
      "last_quality": 0,
      "review_count": 0,
      "added": "2026-05-17"
    },
    "plagiarism": {
      "word": "plagiarism",
      "meaning": "抄袭，剽窃",
      "ipa": "/ˈpleɪdʒərɪzəm/",
      "example": "",
      "ease_factor": 2.5,
      "repetitions": 0,
      "interval": 1,
      "next_review": "2026-05-17",
      "last_quality": 0,
      "review_count": 0,
      "added": "2026-05-17"
    },
    "allegation": {
      "word": "allegation",
      "meaning": "指控，断言",
      "ipa": "/ˌæləˈɡeɪʃn/",
      "example": "",
      "ease_factor": 2.5,
      "repetitions": 0,
      "interval": 1,
      "next_review": "2026-05-17",
      "last_quality": 0,
      "review_count": 0,
      "added": "2026-05-17"
    },
    "georgia": {
      "word": "georgia",
      "meaning": "来自TED深度课",
      "ipa": "",
      "example": "",
      "ease_factor": 2.5,
      "repetitions": 0,
      "interval": 1,
      "next_review": "2026-05-17",
      "last_quality": 0,
      "review_count": 0,
      "added": "2026-05-17"
    },
    "fgettyimages": {
      "word": "fgettyimages",
      "meaning": "来自TED深度课",
      "ipa": "",
      "example": "",
      "ease_factor": 2.5,
      "repetitions": 0,
      "interval": 1,
      "next_review": "2026-05-17",
      "last_quality": 0,
      "review_count": 0,
      "added": "2026-05-17"
    }
  },
  "last_review": "2026-05-17"
}